code/__init__.py
calcsivapriyan-0.1.dist-info/LICENSE.txt
calcsivapriyan-0.1.dist-info/METADATA
calcsivapriyan-0.1.dist-info/WHEEL
calcsivapriyan-0.1.dist-info/top_level.txt
calcsivapriyan-0.1.dist-info/RECORD
