Metadata-Version: 2.1
Name: calcsivapriyan
Version: 0.1
Summary: This is very basic calculator
Author: Sivapriyan M
Author-email: sivapriyan7siva@gmail.com
Classifier: Programming Language :: Python :: 3
Classifier: License :: OSI Approved :: MIT License
Classifier: Operating System :: OS Independent
License-File: LICENSE.txt
